gammarer/aws_budgets_notification/__init__.py
gammarer/aws_budgets_notification/py.typed
gammarer/aws_budgets_notification/_jsii/__init__.py
gammarer/aws_budgets_notification/_jsii/aws-budgets-notification@1.2.7.jsii.tgz
gammarer.aws_budgets_notification-1.2.7.dist-info/LICENSE
gammarer.aws_budgets_notification-1.2.7.dist-info/METADATA
gammarer.aws_budgets_notification-1.2.7.dist-info/WHEEL
gammarer.aws_budgets_notification-1.2.7.dist-info/top_level.txt
gammarer.aws_budgets_notification-1.2.7.dist-info/RECORD
